[
  {
    "source": "Variety",
    "title": "What’s Coming to Disney+ in May 2026",
    "url": "https://variety.com/feature/whats-on-disney-plus-new-shows-movies-1203517920/",
    "description": "",
    "scraped_at": "2026-04-29T01:50:41.002863",
    "published_date": "2026-04-29",
    "content": "ByPayton Turkeltaub\n\nDisney+is heading into May with a packed lineup of premieres, returning favorites and major live sports.\n\nMay kicks off with the premiere of “Sofia the First: Royal Magic” and “Miraculous: Tales of Ladybug and Cat Noir Chibi: Shorts.” ESPN broadcasts begin early, including the men’s lacrosse championship, the PGA championship and, later in the month, the women’s college world series.\n\nOn the entertainment side, new and returning titles arrive across Disney+ and Hulu, with highlights like “We Bought a Zoo,” Season 9 of “American Idol” and Season 2 of “Rivals” available for streaming.\n\nTake a look at Disney+’s full May slate below, and sign up for aDisney+ account here.\n\nMay 1“The Boss (El Encargado)” Season 4 (Premiere) (Hulu Original)“Impuros” Season 6 (Premiere) (Hulu Original)“Magicampers” Season 1 (Disney+)“Perfect Crown” (Hulu Original)“Travis Japan Summer Vacation!! in the USA” (Premiere) (Hulu Original)“We Bought a Zoo” (Hulu)\n\nMay 2“iHeartCountry Festival” (Hulu)“Perfect Crown” (Hulu Original)“UFL – Dallas Renegades at DC Defenders” (ABC, ESPN)“Men’s Lacrosse MAAC Championship” (ESPNU, ESPN)“Men’s Lacrosse Big East Championship” (ESPNU, ESPN)“Women’s Lacrosse Big 12 Championship” (ESPNU, ESPN)\n\nMay 3“Women’s Lacrosse MAAC Championship” (ESPNU, ESPN)“Men’s Lacrosse ACC Championship” (ACCN, ESPN)“Men’s Lacrosse Ivy League Championship” (ESPNU, ESPN)\n\nMay 4“American Idol” Season 9 (ABC, Disney+)“Star Wars: Maul – Shadow Lord” (Finale) (Disney+ Original) (Disney+)\n\nMay 5“Marvel Television’s Daredevil: Born Again” Season 2 (Disney+ Original) (Disney+)\n\nMay 6“Gold Land” (Hulu Original)\n\nMay 8“Miraculous: Tales of Ladybug and Cat Noir Chibi: Shorts” Season 1 (Premiere) (Disney+)“Playdate with Winnie the Pooh: Shorts” Season 3 (Disney+)“Perfect Crown” (Hulu Original)“Travis Japan Summer Vacation!! in the USA” (Hulu Original)“We Bury The Dead” (Hulu)\n\nMay 9“Chibiverse” Season 4 (Premiere) (Disney+)“Perfect Crown” (Hulu Original)“WNBA Season Start – ABC Doubleheader, Game 1” (ABC, ESPN)“WNBA Season Start – ABC Doubleheader, Game 2” (ABC, ESPN)“WWE Backlash” (ESPN)\n\nMay 10“LALIGA ElClásico – FC Barcelona vs. Real Madrid” (ESPN, ESPN Deportes, ESPN+)\n\nMay 11“American Idol” Season 9 (ABC, Disney+)“The Split” (BBC, Hulu)\n\nMay 12“Tucci in Italy” (Premiere) (Disney+ and Hulu)“A Marvel Television Special Presentation: The Punisher: One Last Kill” (Premiere) (Disney+ Original)\n\nMay 13“Battle of Fates (DUBBED)” Season 1 (Hulu Original)“Gold Land” (Hulu Original)“Hey A.J.!” (Disney+)\n\nMay 14“FX’s Welcome to Wrexham” Season 5 (Premiere) (Hulu)“PGA Championship – First Round” (ESPN)“PGA Championship – First Round” (ESPN2, ESPN)\n\nMay 15“Minnie’s Bow-Toons: Pet Hotel” (Disney+)“Lisa Ann Walter: It Was An Accident” (Hulu Original)“Perfect Crown” (Hulu Original)“Rivals” Season 2 (Premiere) (Hulu Original)“Travis Japan Summer Vacation!! in the USA” (Hulu Original)“PGA Championship – Second Round” (ESPN)“PGA Championship – Second Round” (ESPN2, ESPN)\n\nMay 16“Perfect Crown” (Hulu Original)“FA Cup Final” (ESPN)“PGA Championship – Third Round” (ESPN)“UFL – Houston Gamblers at St. Louis Battlehawks” (ABC, ESPN)\n\nMay 17“PGA Championship – Final Round” (ESPN)\n\nMay 18“Battle of Fates (DUBBED)” Season 1 (Hulu Original)\n\nMay 19“The Nightmare Upstairs: What Happened to Ty and Bryn” (Premiere) (Hulu Original)\n\nMay 20“Bluey Minisodes” (Disney+)“Gold Land” (Hulu Original)“NHL: Stanley Cup Playoffs Eastern or Western Conference Final Begins” (ESPN, ABC)\n\nMay 21“Alien: Romulus” (Hulu)\n\nMay 22“Arco” (Hulu)“BeddyByes” Season 1 (Disney+)“Travis Japan Summer Vacation!! in the USA” (Hulu Original)\n\nMay 23“Banana Ball: Bananas vs. Tailgaters” (Disney+, ESPN)“DFB Pokal – German Cup Final” (ESPN)“UFL – Birmingham Stallions at Columbus Aviators” (ABC, ESPN)\n\nMay 24“NCAA Women’s Lacrosse Championship” (ESPN)“NWSL on ESPN+ – Bay FC vs. Chicago Stars” (ESPN+, ESPN)\n\nMay 25“NCAA Men’s Lacrosse Championship” (ESPN)\n\nMay 26“Descendent” (Hulu)“Sofia the First: Royal Magic” (Premiere) (Disney+)\n\nMay 27“Gold Land” (Hulu Original)\n\nMay 28“Deli Boys” (Season 2) (Hulu Original)“Women’s College World Series Game #1” (ESPN)“Women’s College World Series Game #2” (ESPN)“Women’s College World Series Game #3” (ESPN2, ESPN)“Women’s College World Series Game #4” (ESPN2, ESPN)\n\nMay 29“Banana Ball: Party Animals vs. Coconuts” (Disney+ and ESPN)“RoboGobo” Season 2 (Disney+)“Travis Japan Summer Vacation!! in the USA” (Hulu Original)“Women’s College World Series Game #5” (ESPN2, ESPN)“Women’s College World Series Game #6” (ESPN2, ESPN)\n\nMay 30“Women’s College World Series Game #7” (ABC, ESPN)“Women’s College World Series Game #8” (ESPN)\n\nMay 31“WWE Clash” (ESPN)“UFL – Orlando Storm at DC Defenders” (ABC, ESPN)“Women’s College World Series Game #9” (ABC, ESPN)“Women’s College World Series Game #10” (ESPN2, ESPN)",
    "image_url": "https://variety.com/wp-content/uploads/2026/03/Rivals.webp?crop=0px%2C0px%2C1359px%2C765px&resize=1000%2C563",
    "title_zh": "2026年5月，Disney+將推出哪些新內容\n\n隨著2026年5月的到來，Disney+將為觀眾帶來一系列令人期待的新內容。這個月將包括多部電影和電視節目的首播，滿足各年齡層觀眾的需求。\n\n其中，備受矚目的新片包括由導演詹姆斯·卡梅隆(James Cameron)執導的《阿凡達：水之道(Avatar: The Way of Water)》，這部續集將繼續探索潘多拉的奇幻世界。此外，還有迪士尼經典動畫的全新改編版本，將為老少皆宜的觀眾帶來懷舊的同時，注入新的生命。\n\n在電視節目方面，Disney+將推出全新系列《星際大戰：絕地傳承(Star Wars: Jedi Legacy)》，這是一部圍繞絕地武士的冒險故事，將吸引星際大戰的粉絲們。\n\n隨著這些新內容的推出，Disney+將繼續擴展其豐富的媒體庫，為訂閱者提供更多的娛樂選擇。敬請期待！",
    "content_zh": "由佩頓·圖克塔布(Payton Turkeltaub)報導\n\nDisney+將在五月迎來一系列精彩的首映、回歸的熱門節目以及重要的現場體育賽事。\n\n五月將以《公主 Sofia：皇家魔法》(Sofia the First: Royal Magic)和《奇蹟：瓢蟲與黑貓的故事 Chibi：短片》(Miraculous: Tales of Ladybug and Cat Noir Chibi: Shorts)的首映拉開序幕。ESPN的轉播將提前開始，包括男子長曲棍球錦標賽、PGA錦標賽，以及本月稍後的女子大學世界系列賽。\n\n在娛樂方面，Disney+和Hulu將推出新片和回歸的節目，亮點包括《我們買了一座動物園》(We Bought a Zoo)、《美國偶像》(American Idol)第九季和《競爭者》(Rivals)第二季可供串流播放。\n\n以下是Disney+完整的五月節目表，並在這裡註冊Disney+帳戶。\n\n五月一日\n《老闆》(The Boss) 第四季（首映）（Hulu原創）\n《不純》(Impuros) 第六季（首映）（Hulu原創）\n《魔法營地》(Magicampers) 第一季（Disney+）\n《完美王冠》(Perfect Crown)（Hulu原創）\n《Travis Japan 夏季假期!! 在美國》（首映）（Hulu原創）\n《我們買了一座動物園》(We Bought a Zoo)（Hulu）\n\n五月二日\n《iHeartCountry 音樂節》(iHeartCountry Festival)（Hulu）\n《完美王冠》(Perfect Crown)（Hulu原創）\n《UFL – 達拉斯叛逆者對華盛頓防衛者》(UFL – Dallas Renegades at DC Defenders)（ABC, ESPN）\n《男子長曲棍球 MAAC 錦標賽》(Men’s Lacrosse MAAC Championship)（ESPNU, ESPN）\n《男子長曲棍球大東區錦標賽》(Men’s Lacrosse Big East Championship)（ESPNU, ESPN）\n《女子長曲棍球大12區錦標賽》(Women’s Lacrosse Big 12 Championship)（ESPNU, ESPN）\n\n五月三日\n《女子長曲棍球 MAAC 錦標賽》(Women’s Lacrosse MAAC Championship)（ESPNU, ESPN）\n《男子長曲棍球 ACC 錦標賽》(Men’s Lacrosse ACC Championship)（ACCN, ESPN）\n《男子長曲棍球常春藤聯盟錦標賽》(Men’s Lacrosse Ivy League Championship)（ESPNU, ESPN）\n\n五月四日\n《美國偶像》(American Idol) 第九季（ABC, Disney+）\n《星際大戰：莫爾 - 影子之主》(Star Wars: Maul – Shadow Lord)（大結局）（Disney+原創）（Disney+）\n\n五月五日\n《漫威電視的惡棍：重生》(Marvel Television’s Daredevil: Born Again) 第二季（Disney+原創）（Disney+）\n\n五月六日\n《金土地》(Gold Land)（Hulu原創）\n\n五月八日\n《奇蹟：瓢蟲與黑貓的故事 Chibi：短片》(Miraculous: Tales of Ladybug and Cat Noir Chibi: Shorts) 第一季（首映）（Disney+）\n《與小熊維尼的遊戲約會：短片》(Playdate with Winnie the Pooh: Shorts) 第三季（Disney+）\n《完美王冠》(Perfect Crown)（Hulu原創）\n《Travis Japan 夏季假期!! 在美國》（Hulu原創）\n《我們埋葬死者》(We Bury The Dead)（Hulu）\n\n五月九日\n《Chibiverse》第四季（首映）（Disney+）\n《完美王冠》(Perfect Crown)（Hulu原創）\n《WNBA賽季開始 – ABC雙賽，第一場》(WNBA Season Start – ABC Doubleheader, Game 1)（ABC, ESPN）\n《WNBA賽季開始 – ABC雙賽，第二場》(WNBA Season Start – ABC Doubleheader, Game 2)（ABC, ESPN）\n《WWE Backlash》(WWE Backlash)（ESPN）\n\n五月十日\n《LALIGA ElClásico – 巴塞隆納對皇家馬德里》(LALIGA ElClásico – FC Barcelona vs. Real Madrid)（ESPN, ESPN Deportes, ESPN+）\n\n五月十一日\n《美國偶像》(American Idol) 第九季（ABC, Disney+）\n《分裂》(The Split)（BBC, Hulu）\n\n五月十二日\n《圖奇在意大利》(Tucci in Italy)（首映）（Disney+和Hulu）\n《漫威電視特別呈現：惡棍：最後一擊》(A Marvel Television Special Presentation: The Punisher: One Last Kill)（首映）（Disney+原創）\n\n五月十三日\n《命運之戰》(Battle of Fates)（配音）第一季（Hulu原創）\n《金土地》(Gold Land)（Hulu原創）\n《嘿，A.J.!》(Hey A.J.)（Disney+）\n\n五月十四日\n《FX的歡迎來到雷克瑟姆》(FX’s Welcome to Wrexham) 第五季（首映）（Hulu）\n《PGA錦標賽 – 第一輪》(PGA Championship – First Round)（ESPN）\n《PGA錦標賽 – 第一輪》(PGA Championship – First Round)（ESPN2, ESPN）\n\n5月15日  \n《米妮的蝴蝶結動畫：寵物酒店》(Minnie’s Bow-Toons: Pet Hotel)（Disney+）  \n《莉莎·安·沃爾特：這是一個意外》(Lisa Ann Walter: It Was An Accident)（Hulu Original）  \n《完美的冠冕》(Perfect Crown)（Hulu Original）  \n《競爭者》第2季（首播）(Rivals Season 2)（Hulu Original）  \n《特拉維斯·日本夏季假期！！在美國》(Travis Japan Summer Vacation!! in the USA)（Hulu Original）  \n《PGA錦標賽 – 第二輪》(PGA Championship – Second Round)（ESPN）  \n《PGA錦標賽 – 第二輪》(PGA Championship – Second Round)（ESPN2, ESPN）  \n\n5月16日  \n《完美的冠冕》(Perfect Crown)（Hulu Original）  \n《足總杯決賽》(FA Cup Final)（ESPN）  \n《PGA錦標賽 – 第三輪》(PGA Championship – Third Round)（ESPN）  \n《UFL – 休士頓賭徒對聖路易斯猛鷹》(UFL – Houston Gamblers at St. Louis Battlehawks)（ABC, ESPN）  \n\n5月17日  \n《PGA錦標賽 – 最終輪》(PGA Championship – Final Round)（ESPN）  \n\n5月18日  \n《命運之戰（配音版）》(Battle of Fates (DUBBED)) 第1季（Hulu Original）  \n\n5月19日  \n《樓上的噩夢：泰和布林發生了什麼》(The Nightmare Upstairs: What Happened to Ty and Bryn)（首播）（Hulu Original）  \n\n5月20日  \n《藍色小狗迷你集》(Bluey Minisodes)（Disney+）  \n《金土地》(Gold Land)（Hulu Original）  \n《NHL：斯坦利盃季後賽東部或西部決賽開始》(NHL: Stanley Cup Playoffs Eastern or Western Conference Final Begins)（ESPN, ABC）  \n\n5月21日  \n《外星人：羅穆盧斯》(Alien: Romulus)（Hulu）  \n\n5月22日  \n《阿爾科》(Arco)（Hulu）  \n《小公主蘇菲亞：皇家魔法》(BeddyByes) 第1季（Disney+）  \n《特拉維斯·日本夏季假期！！在美國》(Travis Japan Summer Vacation!! in the USA)（Hulu Original）  \n\n5月23日  \n《香蕉球：香蕉隊對尾隨者》(Banana Ball: Bananas vs. Tailgaters)（Disney+, ESPN）  \n《DFB盃 – 德國杯決賽》(DFB Pokal – German Cup Final)（ESPN）  \n《UFL – 伯明翰雄駿對哥倫布飛行員》(UFL – Birmingham Stallions at Columbus Aviators)（ABC, ESPN）  \n\n5月24日  \n《NCAA女子長曲棍球錦標賽》(NCAA Women’s Lacrosse Championship)（ESPN）  \n《NWSL在ESPN+ – 灣FC對芝加哥明星》(NWSL on ESPN+ – Bay FC vs. Chicago Stars)（ESPN+, ESPN）  \n\n5月25日  \n《NCAA男子長曲棍球錦標賽》(NCAA Men’s Lacrosse Championship)（ESPN）  \n\n5月26日  \n《後裔》(Descendent)（Hulu）  \n《小公主蘇菲亞：皇家魔法》(Sofia the First: Royal Magic)（首播）（Disney+）  \n\n5月27日  \n《金土地》(Gold Land)（Hulu Original）  \n\n5月28日  \n《熟食男孩》第2季（Deli Boys）(Hulu Original)  \n《女子大學世界系列第一場比賽》(Women’s College World Series Game #1)（ESPN）  \n《女子大學世界系列第二場比賽》(Women’s College World Series Game #2)（ESPN）  \n《女子大學世界系列第三場比賽》(Women’s College World Series Game #3)（ESPN2, ESPN）  \n《女子大學世界系列第四場比賽》(Women’s College World Series Game #4)（ESPN2, ESPN）  \n\n5月29日  \n《香蕉球：派對動物對椰子隊》(Banana Ball: Party Animals vs. Coconuts)（Disney+ 和 ESPN）  \n《機器人歌舞》(RoboGobo) 第2季（Disney+）  \n《特拉維斯·日本夏季假期！！在美國》(Travis Japan Summer Vacation!! in the USA)（Hulu Original）  \n《女子大學世界系列第五場比賽》(Women’s College World Series Game #5)（ESPN2, ESPN）  \n《女子大學世界系列第六場比賽》(Women’s College World Series Game #6)（ESPN2, ESPN）  \n\n5月30日  \n《女子大學世界系列第七場比賽》(Women’s College World Series Game #7)（ABC, ESPN）  \n《女子大學世界系列第八場比賽》(Women’s College World Series Game #8)（ESPN）  \n\n5月31日  \n《WWE對抗賽》(WWE Clash)（ESPN）  \n《UFL – 奧蘭多風暴對華盛頓防衛者》(UFL – Orlando Storm at DC Defenders)（ABC, ESPN）  \n《女子大學世界系列第九場比賽》(Women’s College World Series Game #9)（ABC, ESPN）  \n《女子大學世界系列第十場比賽》(Women’s College World Series Game #10)（ESPN2, ESPN）",
    "summary_zh": "由佩頓·圖克塔布(Payton Turkeltaub)報導\n\nDisney+將在五月迎來一系列精彩的首映、回歸的熱門節目以及重要的現場體育賽事。\n\n五月將以《公主 Sofia：皇家魔法》(Sofia the First: Royal Magic)和《奇蹟：瓢蟲與黑貓的故事 Chibi：短片》(Miraculous: Tales of Ladybug and Cat Noir Chibi: Shor...",
    "slug": "whats-coming-to-disney-in-may-2026",
    "id": "2026-04-29-variety-whats-coming-to-disney-in-may-"
  }
]